Workbook

Sheet Read me
A1: Checkers read — Creative Beverages
A2: Built at the Entrepreneur Coach workshop, 22 August 2026
A5: What this is
B6: Your two Checkers exports turned into the three answers you asked for:
B7: who is out of stock, what is selling, and what is not.
B8: Patch is reported separately from the core range, the way Checkers
B9: already structures the account (vendor 196005, sub-ranges 01 and 02).
A11: How to refresh it next week
B12: 1. Download both exports from Checkers as usual
B13: 2. Ask Claude: "rebuild my Checkers read from these two files"
B14: 3. Everything on the other sheets recalculates. Nothing to retype.
A16: Three things this gets right that a quick look gets wrong
B17: 1. Every article appears once per pack — single, 4-pack, 24-pack.
B18: Those are different products on shelf with their own sales, so
B19: rand values are added across them. Ignore the multipacks and you
B20: lose most of the revenue: Margarita is R374k, of which R320k is
B21: the 4-pack alone.
B22: 2. Units are not comparable across those rows — one counts single
B23: cans, the next counts 4-packs. They are converted to eaches
B24: (units x pack size) before being added.
B25: 3. Store counts repeat on every pack row, so the highest is taken
B26: per article rather than the sum. Checkers' own total sheet sums
B27: them, which is why its listing count reads about 3x too high.
A29: Checked against source
B30: Totals on this workbook reconcile exactly to the 'Vendor and VSR
B31: Total View' sheet in each export: R803,732.61 core, R954,647.47 Patch.
A33: Still to confirm with you
B34: · Negroni and Old Fashioned show 0 active stores but did sell.
B35: Is 'active' a current-range flag rather than sold-in-period?
B36: · Sales are the latest period, excluding VAT, as Checkers reports them.

Sheet Summary
A1: Summary
A2: Latest period. Patch and the core range kept apart, as Checkers structures them.
B4: Patch | C4: Core range | D4: Total
A5: Sales (excl VAT) | B5: =SUMIF('By product'!$A$5:$A$37,B$4,'By product'!$H$5:$H$37) | C5: =SUMIF('By product'!$A$5:$A$37,C$4,'By product'!$H$5:$H$37) | D5: =B5+C5
A6: Eaches sold, latest week | B6: =SUMIF('By product'!$A$5:$A$37,B$4,'By product'!$G$5:$G$37) | C6: =SUMIF('By product'!$A$5:$A$37,C$4,'By product'!$G$5:$G$37) | D6: =B6+C6
A7: Products listed | B7: =COUNTIF('By product'!$A$5:$A$37,B$4) | C7: =COUNTIF('By product'!$A$5:$A$37,C$4) | D7: =B7+C7
A8: Products actually selling | B8: =COUNTIFS('By product'!$A$5:$A$37,B$4,'By product'!$H$5:$H$37,">0") | C8: =COUNTIFS('By product'!$A$5:$A$37,C$4,'By product'!$H$5:$H$37,">0") | D8: =B8+C8
A9: Listings | B9: =SUMIF('By product'!$A$5:$A$37,B$4,'By product'!$D$5:$D$37) | C9: =SUMIF('By product'!$A$5:$A$37,C$4,'By product'!$D$5:$D$37) | D9: =B9+C9
A10: Active store slots | B10: =SUMIF('By product'!$A$5:$A$37,B$4,'By product'!$E$5:$E$37) | C10: =SUMIF('By product'!$A$5:$A$37,C$4,'By product'!$E$5:$E$37) | D10: =B10+C10
A11: Activation rate | B11: =IF(B9=0,"",B10/B9) | C11: =IF(C9=0,"",C10/C9) | D11: =IF(D9=0,"",D10/D9)
A13: Patch is 6 products. The core range is 27. Read the sales line next to that.

Sheet Distribution gaps
A1: Distribution gaps
A2: Where you have a listing and no sale. Sorted by the size of the gap.
A4: Portfolio | B4: Article | C4: Listed stores | D4: Active stores | E4: Activation | F4: Stores not selling
A5: Core | B5: BEER KRYSTEL WEISS CBC 340ML BOT | C5: 958 | D5: 136 | E5: =IF(C5=0,"",D5/C5) | F5: =C5-D5
A6: Core | B6: BEER PILSNER CBC 340ML NRB | C6: 960 | D6: 138 | E6: =IF(C6=0,"",D6/C6) | F6: =C6-D6
A7: Core | B7: BEER ALE PALE CBC 340ML NRB | C7: 950 | D7: 131 | E7: =IF(C7=0,"",D7/C7) | F7: =C7-D7
A8: Core | B8: BEER LAGER CBC 340ML BOT | C8: 961 | D8: 143 | E8: =IF(C8=0,"",D8/C8) | F8: =C8-D8
A9: Core | B9: BEER LAGER LITE CBC 340ML NRB | C9: 947 | D9: 143 | E9: =IF(C9=0,"",D9/C9) | F9: =C9-D9
A10: Core | B10: BEER AMBER WEISS CBC 440ML NRB | C10: 862 | D10: 124 | E10: =IF(C10=0,"",D10/C10) | F10: =C10-D10
A11: Core | B11: BEER LAGER TRUEMAN 660ML NRB | C11: 473 | D11: 0 | E11: =IF(C11=0,"",D11/C11) | F11: =C11-D11
A12: Core | B12: GIN&TONIC N-ALC BOTANICL THE DUCHES300ML | C12: 343 | D12: 0 | E12: =IF(C12=0,"",D12/C12) | F12: =C12-D12
A13: Core | B13: GIN&TONIC N-ALC FLORAL THE DUCHESS 300ML | C13: 343 | D13: 0 | E13: =IF(C13=0,"",D13/C13) | F13: =C13-D13
A14: Core | B14: CIDER REKORDERLIG 500ML BOT, WILD BERRY | C14: 331 | D14: 0 | E14: =IF(C14=0,"",D14/C14) | F14: =C14-D14
A15: Patch | B15: COCKTAIL PATCH 150ML, NEGRONI | C15: 225 | D15: 0 | E15: =IF(C15=0,"",D15/C15) | F15: =C15-D15
A16: Patch | B16: COCKTAIL PATCH 150ML, OLD FASHIONED | C16: 225 | D16: 0 | E16: =IF(C16=0,"",D16/C16) | F16: =C16-D16
... A37: Patch | B37: COCKTAIL PATCH 150ML, ESPRES MARTINI | C37: 359 | D37: 359 | E37: =IF(C37=0,"",D37/C37) | F37: =C37-D37
A39: Shaded rows are listed in Checkers and selling in no store at all.

Sheet Data
A1: Data
A2: One row per article and pack, straight from the exports. Blue cells come from the file.
A4: Portfolio | B4: Article key | C4: Article | D4: Pack | E4: Pack size | F4: Sell price (incl) | G4: 12.07.2026 units | H4: 19.07.2026 units | I4: 26.07.2026 units | J4: 02.08.2026 units | K4: 09.08.2026 units | L4: 16.08.2026 units | M4: Eaches, latest week | N4: Sales (excl VAT) | O4: Stock qty
A5: Core | B5: 10755051 | C5: BEER LAGER TRUEMAN 660ML NRB | D5: 12X660ML NRB | E5: 12 | F5: 240 | G5: 0 | H5: 0 | I5: 0 | J5: 0 | K5: 0 | L5: 0 | M5: =L5*E5 | N5: 0 | O5: 0
A6: Core | B6: 10755051 | C6: BEER LAGER TRUEMAN 660ML NRB | D6: 12X660ML NRB | E6: 12 | F6: 240 | G6: 0 | H6: 0 | I6: 0 | J6: 0 | K6: 0 | L6: 0 | M6: =L6*E6 | N6: 0 | O6: 0
A7: Core | B7: 10755051 | C7: BEER LAGER TRUEMAN 660ML NRB | D7: 660ML NRB | E7: 1 | F7: 20 | G7: 0 | H7: 0 | I7: 0 | J7: 0 | K7: 0 | L7: 0 | M7: =L7*E7 | N7: 0 | O7: 19
A8: Core | B8: 10755051 | C8: BEER LAGER TRUEMAN 660ML NRB | D8: 660ML NRB | E8: 1 | F8: 20 | G8: 0 | H8: 0 | I8: 0 | J8: 0 | K8: 0 | L8: 0 | M8: =L8*E8 | N8: 0 | O8: 0
A9: Core | B9: 10969386 | C9: BEER MILK STOUT CBC 340ML NRB | D9: 24X340ML NRB | E9: 24 | F9: 379.99 | G9: 0 | H9: 0 | I9: 0 | J9: 0 | K9: 0 | L9: 0 | M9: =L9*E9 | N9: 0 | O9: 0
A10: Core | B10: 10969386 | C10: BEER MILK STOUT CBC 340ML NRB | D10: 340ML NRB | E10: 1 | F10: 19.99 | G10: 0 | H10: 0 | I10: 0 | J10: 1 | K10: 18 | L10: 44 | M10: =L10*E10 | N10: 764.79 | O10: 7674
A11: Core | B11: 10969386 | C11: BEER MILK STOUT CBC 340ML NRB | D11: 6X340ML NRB | E11: 6 | F11: 109.99 | G11: 0 | H11: 0 | I11: 0 | J11: 2 | K11: 13 | L11: 25 | M11: =L11*E11 | N11: 2391 | O11: 0
A12: Core | B12: 10711455 | C12: BEER LAGER LITE CBC 340ML NRB | D12: 24X340ML NRB | E12: 24 | F12: 359.99 | G12: 4 | H12: 1 | I12: 1 | J12: 1 | K12: 5 | L12: 2 | M12: =L12*E12 | N12: 626.06 | O12: 0
A13: Core | B13: 10711455 | C13: BEER LAGER LITE CBC 340ML NRB | D13: 340ML NRB | E13: 1 | F13: 18.99 | G13: 14 | H13: 23 | I13: 15 | J13: 18 | K13: 17 | L13: 23 | M13: =L13*E13 | N13: 379.74 | O13: 9841
A14: Core | B14: 10711455 | C14: BEER LAGER LITE CBC 340ML NRB | D14: 6X340ML NRB | E14: 6 | F14: 99.99 | G14: 161 | H14: 175 | I14: 132 | J14: 180 | K14: 184 | L14: 139 | M14: =L14*E14 | N14: 10955.08 | O14: 0
A15: Core | B15: 10483607 | C15: BEER AMBER WEISS CBC 440ML NRB | D15: 24X440ML NRB | E15: 24 | F15: 609.99 | G15: 0 | H15: 0 | I15: 0 | J15: 0 | K15: 0 | L15: 0 | M15: =L15*E15 | N15: 0 | O15: 0
A16: Core | B16: 10483607 | C16: BEER AMBER WEISS CBC 440ML NRB | D16: 24X440ML NRB | E16: 24 | F16: 609.99 | G16: 0 | H16: 1 | I16: 0 | J16: 1 | K16: 0 | L16: 0 | M16: =L16*E16 | N16: 0 | O16: 0
... A128: Patch | B128: 10938917 | C128: COCKTAIL PATCH 150ML, OLD FASHIONED | D128: 4X150ML CAN | E128: 4 | F128: 159.99 | G128: 2 | H128: 2 | I128: 4 | J128: 1 | K128: 3 | L128: 1 | M128: =L128*E128 | N128: 139.12 | O128: 0

Sheet By product
A1: By product
A2: Money and units come from Data. Store counts are the max across pack rows.
A4: Portfolio | B4: Article key | C4: Article | D4: Listed stores | E4: Active stores | F4: Activation | G4: Eaches, latest week | H4: Sales (excl VAT) | I4: Share of portfolio
A5: Core | B5: 10483607 | C5: BEER AMBER WEISS CBC 440ML NRB | D5: 862 | E5: 124 | F5: =IF(D5=0,"",E5/D5) | G5: =SUMIF(Data!$B$5:$B$128,$B5,Data!$M$5:$M$128) | H5: =SUMIF(Data!$B$5:$B$128,$B5,Data!$N$5:$N$128) | I5: =IF(SUMIF($A:$A,$A5,$H:$H)=0,"",H5/SUMIF($A:$A,$A5,$H:$H))
A6: Core | B6: 10483608 | C6: BEER PILSNER CBC 440ML NRB | D6: 9 | E6: 0 | F6: =IF(D6=0,"",E6/D6) | G6: =SUMIF(Data!$B$5:$B$128,$B6,Data!$M$5:$M$128) | H6: =SUMIF(Data!$B$5:$B$128,$B6,Data!$N$5:$N$128) | I6: =IF(SUMIF($A:$A,$A6,$H:$H)=0,"",H6/SUMIF($A:$A,$A6,$H:$H))
A7: Core | B7: 10521085 | C7: BEER ALE PALE CBC 330ML CAN | D7: 9 | E7: 0 | F7: =IF(D7=0,"",E7/D7) | G7: =SUMIF(Data!$B$5:$B$128,$B7,Data!$M$5:$M$128) | H7: =SUMIF(Data!$B$5:$B$128,$B7,Data!$N$5:$N$128) | I7: =IF(SUMIF($A:$A,$A7,$H:$H)=0,"",H7/SUMIF($A:$A,$A7,$H:$H))
A8: Core | B8: 10532818 | C8: BEER KRYSTEL WEISS CBC 340ML BOT | D8: 958 | E8: 136 | F8: =IF(D8=0,"",E8/D8) | G8: =SUMIF(Data!$B$5:$B$128,$B8,Data!$M$5:$M$128) | H8: =SUMIF(Data!$B$5:$B$128,$B8,Data!$N$5:$N$128) | I8: =IF(SUMIF($A:$A,$A8,$H:$H)=0,"",H8/SUMIF($A:$A,$A8,$H:$H))
A9: Core | B9: 10532819 | C9: BEER LAGER CBC 340ML BOT | D9: 961 | E9: 143 | F9: =IF(D9=0,"",E9/D9) | G9: =SUMIF(Data!$B$5:$B$128,$B9,Data!$M$5:$M$128) | H9: =SUMIF(Data!$B$5:$B$128,$B9,Data!$N$5:$N$128) | I9: =IF(SUMIF($A:$A,$A9,$H:$H)=0,"",H9/SUMIF($A:$A,$A9,$H:$H))
A10: Core | B10: 10615602 | C10: CIDER REKORDERLIG 500ML BOT, WILD BERRY | D10: 331 | E10: 0 | F10: =IF(D10=0,"",E10/D10) | G10: =SUMIF(Data!$B$5:$B$128,$B10,Data!$M$5:$M$128) | H10: =SUMIF(Data!$B$5:$B$128,$B10,Data!$N$5:$N$128) | I10: =IF(SUMIF($A:$A,$A10,$H:$H)=0,"",H10/SUMIF($A:$A,$A10,$H:$H))
A11: Core | B11: 10615603 | C11: CIDER REKORDERLIG 500ML BOT, STRAWB LIME | D11: 5 | E11: 0 | F11: =IF(D11=0,"",E11/D11) | G11: =SUMIF(Data!$B$5:$B$128,$B11,Data!$M$5:$M$128) | H11: =SUMIF(Data!$B$5:$B$128,$B11,Data!$N$5:$N$128) | I11: =IF(SUMIF($A:$A,$A11,$H:$H)=0,"",H11/SUMIF($A:$A,$A11,$H:$H))
A12: Core | B12: 10697191 | C12: BEER PILSNER CBC 340ML NRB | D12: 960 | E12: 138 | F12: =IF(D12=0,"",E12/D12) | G12: =SUMIF(Data!$B$5:$B$128,$B12,Data!$M$5:$M$128) | H12: =SUMIF(Data!$B$5:$B$128,$B12,Data!$N$5:$N$128) | I12: =IF(SUMIF($A:$A,$A12,$H:$H)=0,"",H12/SUMIF($A:$A,$A12,$H:$H))
A13: Core | B13: 10711455 | C13: BEER LAGER LITE CBC 340ML NRB | D13: 947 | E13: 143 | F13: =IF(D13=0,"",E13/D13) | G13: =SUMIF(Data!$B$5:$B$128,$B13,Data!$M$5:$M$128) | H13: =SUMIF(Data!$B$5:$B$128,$B13,Data!$N$5:$N$128) | I13: =IF(SUMIF($A:$A,$A13,$H:$H)=0,"",H13/SUMIF($A:$A,$A13,$H:$H))
A14: Core | B14: 10755051 | C14: BEER LAGER TRUEMAN 660ML NRB | D14: 473 | E14: 0 | F14: =IF(D14=0,"",E14/D14) | G14: =SUMIF(Data!$B$5:$B$128,$B14,Data!$M$5:$M$128) | H14: =SUMIF(Data!$B$5:$B$128,$B14,Data!$N$5:$N$128) | I14: =IF(SUMIF($A:$A,$A14,$H:$H)=0,"",H14/SUMIF($A:$A,$A14,$H:$H))
A15: Core | B15: 10787565 | C15: CIDER STRAWB LIME REKORDERLIG 330ML CAN | D15: 935 | E15: 934 | F15: =IF(D15=0,"",E15/D15) | G15: =SUMIF(Data!$B$5:$B$128,$B15,Data!$M$5:$M$128) | H15: =SUMIF(Data!$B$5:$B$128,$B15,Data!$N$5:$N$128) | I15: =IF(SUMIF($A:$A,$A15,$H:$H)=0,"",H15/SUMIF($A:$A,$A15,$H:$H))
A16: Core | B16: 10810779 | C16: BEER ALE PALE CBC 340ML NRB | D16: 950 | E16: 131 | F16: =IF(D16=0,"",E16/D16) | G16: =SUMIF(Data!$B$5:$B$128,$B16,Data!$M$5:$M$128) | H16: =SUMIF(Data!$B$5:$B$128,$B16,Data!$N$5:$N$128) | I16: =IF(SUMIF($A:$A,$A16,$H:$H)=0,"",H16/SUMIF($A:$A,$A16,$H:$H))
... A37: Core | B37: 10969386 | C37: BEER MILK STOUT CBC 340ML NRB | D37: 143 | E37: 138 | F37: =IF(D37=0,"",E37/D37) | G37: =SUMIF(Data!$B$5:$B$128,$B37,Data!$M$5:$M$128) | H37: =SUMIF(Data!$B$5:$B$128,$B37,Data!$N$5:$N$128) | I37: =IF(SUMIF($A:$A,$A37,$H:$H)=0,"",H37/SUMIF($A:$A,$A37,$H:$H))
